LICENSE
MANIFEST.in
README.md
setup.py
tf1/__init__.py
tf1.egg-info/PKG-INFO
tf1.egg-info/SOURCES.txt
tf1.egg-info/dependency_links.txt
tf1.egg-info/requires.txt
tf1.egg-info/top_level.txt
tf1/tests/__init__.py